{
  "cloned_from_module_id" : 7557899,
  "contains_overridable_hubl_tags" : false,
  "content_tags" : [ ],
  "css_assets" : [ ],
  "editable_contexts" : [ ],
  "external_js" : [ ],
  "extra_classes" : "",
  "global" : false,
  "help_text" : "",
  "host_template_types" : [ "PAGE", "BLOG_POST", "BLOG_LISTING" ],
  "js_assets" : [ ],
  "js_cdn_uri" : "https://cdn2.hubspot.net/hub/2660705/hub_generated/module_assets/1556150221978/module_9109043181_belch-modules_Material_Submit_Button.js",
  "label" : "Material Submit Button",
  "js_min_cdn_uri" : "https://cdn2.hubspot.net/hub/2660705/hub_generated/module_assets/1556150222043/module_9109043181_belch-modules_Material_Submit_Button.min.js",
  "other_assets" : [ ],
  "placement_rules" : [ ],
  "purchased" : false,
  "smart_type" : "NOT_SMART",
  "tags" : [ ],
  "portal_id" : 2660705,
  "id" : 9109043181,
  "module_id" : 7560365,
  "is_available_for_new_content" : true
}
